flake8_dunder_class_obj/__init__.py
flake8_dunder_class_obj/version.py
flake8_dunder_class_obj-0.1.1.dist-info/LICENSE
flake8_dunder_class_obj-0.1.1.dist-info/METADATA
flake8_dunder_class_obj-0.1.1.dist-info/WHEEL
flake8_dunder_class_obj-0.1.1.dist-info/entry_points.txt
flake8_dunder_class_obj-0.1.1.dist-info/top_level.txt
flake8_dunder_class_obj-0.1.1.dist-info/RECORD
